COPYING
README.md
setup.py
gripcontrol.egg-info/PKG-INFO
gripcontrol.egg-info/SOURCES.txt
gripcontrol.egg-info/dependency_links.txt
gripcontrol.egg-info/requires.txt
gripcontrol.egg-info/top_level.txt
src/__init__.py
src/channel.py
src/gripcontrol.py
src/grippubcontrol.py
src/httpresponseformat.py
src/httpstreamformat.py
src/response.py
src/websocketcontext.py
src/websocketevent.py
src/websocketmessageformat.py